{
"meta":{"test_sets":[],"test_metrics":[],"learn_metrics":[{"best_value":"Min","name":"RMSE"}],"launch_mode":"Train","parameters":"","iteration_count":171,"learn_sets":["learn"],"name":"experiment"},
"iterations":[
{"learn":[1.441018287],"iteration":0,"passed_time":0.008059535644,"remaining_time":1.37012106},
{"learn":[1.407219859],"iteration":1,"passed_time":0.0150610951,"remaining_time":1.272662536},
{"learn":[1.378068074],"iteration":2,"passed_time":0.02136141975,"remaining_time":1.196239506},
{"learn":[1.352986581],"iteration":3,"passed_time":0.04098146087,"remaining_time":1.710975991},
{"learn":[1.332554065],"iteration":4,"passed_time":0.04887538704,"remaining_time":1.62266285},
{"learn":[1.315290567],"iteration":5,"passed_time":0.05684118536,"remaining_time":1.563132597},
{"learn":[1.300250512],"iteration":6,"passed_time":0.06376525724,"remaining_time":1.493928884},
{"learn":[1.288253459],"iteration":7,"passed_time":0.0961306766,"remaining_time":1.958662536},
{"learn":[1.277178482],"iteration":8,"passed_time":0.1033331137,"remaining_time":1.859996046},
{"learn":[1.268361658],"iteration":9,"passed_time":0.1091354517,"remaining_time":1.757080772},
{"learn":[1.26076487],"iteration":10,"passed_time":0.1153346235,"remaining_time":1.677594523},
{"learn":[1.254225092],"iteration":11,"passed_time":0.1217030544,"remaining_time":1.612565471},
{"learn":[1.248612902],"iteration":12,"passed_time":0.1277107463,"remaining_time":1.552176763},
{"learn":[1.243985106],"iteration":13,"passed_time":0.1366359765,"remaining_time":1.532274879},
{"learn":[1.23997883],"iteration":14,"passed_time":0.1430641812,"remaining_time":1.487867484},
{"learn":[1.236304938],"iteration":15,"passed_time":0.1498410183,"remaining_time":1.451584865},
{"learn":[1.233292139],"iteration":16,"passed_time":0.1567904555,"remaining_time":1.420337067},
{"learn":[1.230697187],"iteration":17,"passed_time":0.1632974725,"remaining_time":1.388028516},
{"learn":[1.228492029],"iteration":18,"passed_time":0.1695132608,"remaining_time":1.356106086},
{"learn":[1.226436506],"iteration":19,"passed_time":0.1755821276,"remaining_time":1.325645063},
{"learn":[1.224791003],"iteration":20,"passed_time":0.1826354923,"remaining_time":1.304539231},
{"learn":[1.223226082],"iteration":21,"passed_time":0.1889230773,"remaining_time":1.279524478},
{"learn":[1.221927612],"iteration":22,"passed_time":0.1961965836,"remaining_time":1.262482364},
{"learn":[1.220608466],"iteration":23,"passed_time":0.2027936172,"remaining_time":1.242110905},
{"learn":[1.219546191],"iteration":24,"passed_time":0.2093489066,"remaining_time":1.222597615},
{"learn":[1.218366036],"iteration":25,"passed_time":0.2155759978,"remaining_time":1.202250757},
{"learn":[1.217560242],"iteration":26,"passed_time":0.2229608268,"remaining_time":1.189124409},
{"learn":[1.21678458],"iteration":27,"passed_time":0.2318740847,"remaining_time":1.184214075},
{"learn":[1.216032611],"iteration":28,"passed_time":0.2381374263,"remaining_time":1.166052225},
{"learn":[1.215399223],"iteration":29,"passed_time":0.2453876174,"remaining_time":1.153321802},
{"learn":[1.214730447],"iteration":30,"passed_time":0.2519189311,"remaining_time":1.137698398},
{"learn":[1.21415929],"iteration":31,"passed_time":0.2579751717,"remaining_time":1.120579652},
{"learn":[1.21359515],"iteration":32,"passed_time":0.2643092615,"remaining_time":1.105293275},
{"learn":[1.213100305],"iteration":33,"passed_time":0.2700683591,"remaining_time":1.088216624},
{"learn":[1.212718489],"iteration":34,"passed_time":0.2769713582,"remaining_time":1.076231563},
{"learn":[1.212364211],"iteration":35,"passed_time":0.2829454436,"remaining_time":1.061045413},
{"learn":[1.211997317],"iteration":36,"passed_time":0.2896074515,"remaining_time":1.048848608},
{"learn":[1.211648373],"iteration":37,"passed_time":0.2962392149,"remaining_time":1.036837252},
{"learn":[1.211229319],"iteration":38,"passed_time":0.3039986592,"remaining_time":1.028918539},
{"learn":[1.210991164],"iteration":39,"passed_time":0.3101286945,"remaining_time":1.015671474},
{"learn":[1.21065402],"iteration":40,"passed_time":0.3163835364,"remaining_time":1.00316731},
{"learn":[1.210332816],"iteration":41,"passed_time":0.3227840199,"remaining_time":0.991408061},
{"learn":[1.210080321],"iteration":42,"passed_time":0.3282464985,"remaining_time":0.9771058559},
{"learn":[1.2097949],"iteration":43,"passed_time":0.3342503215,"remaining_time":0.9647679733},
{"learn":[1.209544284],"iteration":44,"passed_time":0.3392854946,"remaining_time":0.9499993849},
{"learn":[1.209259257],"iteration":45,"passed_time":0.3447121206,"remaining_time":0.9367177189},
{"learn":[1.209037524],"iteration":46,"passed_time":0.3509586334,"remaining_time":0.9259334159},
{"learn":[1.208755581],"iteration":47,"passed_time":0.3564108436,"remaining_time":0.9133027867},
{"learn":[1.208590184],"iteration":48,"passed_time":0.3617161676,"remaining_time":0.9005994378},
{"learn":[1.20835923],"iteration":49,"passed_time":0.367585541,"remaining_time":0.8895570091},
{"learn":[1.208143152],"iteration":50,"passed_time":0.3735899713,"remaining_time":0.8790352266},
{"learn":[1.207938619],"iteration":51,"passed_time":0.3813975701,"remaining_time":0.87281367},
{"learn":[1.207748689],"iteration":52,"passed_time":0.3872854253,"remaining_time":0.8622581167},
{"learn":[1.207629501],"iteration":53,"passed_time":0.3930312139,"remaining_time":0.8515676302},
{"learn":[1.207450817],"iteration":54,"passed_time":0.3987404993,"remaining_time":0.8409799621},
{"learn":[1.207284871],"iteration":55,"passed_time":0.4071638485,"remaining_time":0.836140046},
{"learn":[1.207129017],"iteration":56,"passed_time":0.4133009003,"remaining_time":0.8266018005},
{"learn":[1.206964659],"iteration":57,"passed_time":0.4188172553,"remaining_time":0.8159715492},
{"learn":[1.20676701],"iteration":58,"passed_time":0.4250398787,"remaining_time":0.806855363},
{"learn":[1.206628021],"iteration":59,"passed_time":0.4308358608,"remaining_time":0.7970463425},
{"learn":[1.206489921],"iteration":60,"passed_time":0.4389139456,"remaining_time":0.7914841643},
{"learn":[1.206359468],"iteration":61,"passed_time":0.4449378404,"remaining_time":0.7822294292},
{"learn":[1.206256995],"iteration":62,"passed_time":0.4505413667,"remaining_time":0.7723566287},
{"learn":[1.206069491],"iteration":63,"passed_time":0.4563947063,"remaining_time":0.7630348996},
{"learn":[1.20590382],"iteration":64,"passed_time":0.4618197663,"remaining_time":0.7531214651},
{"learn":[1.205765562],"iteration":65,"passed_time":0.4672609227,"remaining_time":0.7433696498},
{"learn":[1.205657216],"iteration":66,"passed_time":0.4726328503,"remaining_time":0.7336390513},
{"learn":[1.20551482],"iteration":67,"passed_time":0.4788323251,"remaining_time":0.7252901395},
{"learn":[1.205375334],"iteration":68,"passed_time":0.4849045795,"remaining_time":0.7168154654},
{"learn":[1.205210278],"iteration":69,"passed_time":0.490397997,"remaining_time":0.7075742528},
{"learn":[1.205014299],"iteration":70,"passed_time":0.4962475976,"remaining_time":0.6989402784},
{"learn":[1.204886112],"iteration":71,"passed_time":0.5029071013,"remaining_time":0.6914972642},
{"learn":[1.204750346],"iteration":72,"passed_time":0.510679664,"remaining_time":0.68556996},
{"learn":[1.204581036],"iteration":73,"passed_time":0.5165021406,"remaining_time":0.6770365897},
{"learn":[1.20443279],"iteration":74,"passed_time":0.5229901855,"remaining_time":0.6694274374},
{"learn":[1.204313624],"iteration":75,"passed_time":0.5286604652,"remaining_time":0.6608255815},
{"learn":[1.204151183],"iteration":76,"passed_time":0.5350625448,"remaining_time":0.6531932365},
{"learn":[1.203995392],"iteration":77,"passed_time":0.5415225178,"remaining_time":0.6456614635},
{"learn":[1.203870036],"iteration":78,"passed_time":0.547619752,"remaining_time":0.6377343948},
{"learn":[1.203765248],"iteration":79,"passed_time":0.5537124682,"remaining_time":0.6298479325},
{"learn":[1.203631792],"iteration":80,"passed_time":0.5598261506,"remaining_time":0.6220290562},
{"learn":[1.203496541],"iteration":81,"passed_time":0.5666494838,"remaining_time":0.6150220007},
{"learn":[1.203345993],"iteration":82,"passed_time":0.5721862455,"remaining_time":0.6066552965},
{"learn":[1.203218147],"iteration":83,"passed_time":0.5813285528,"remaining_time":0.6020902868},
{"learn":[1.203075029],"iteration":84,"passed_time":0.587496126,"remaining_time":0.5944078451},
{"learn":[1.203011308],"iteration":85,"passed_time":0.5927245262,"remaining_time":0.5858323805},
{"learn":[1.202953977],"iteration":86,"passed_time":0.598577446,"remaining_time":0.5779368445},
{"learn":[1.202838682],"iteration":87,"passed_time":0.6049081885,"remaining_time":0.5705384051},
{"learn":[1.202679787],"iteration":88,"passed_time":0.6110936784,"remaining_time":0.5630301307},
{"learn":[1.202614395],"iteration":89,"passed_time":0.6192210961,"remaining_time":0.5572989865},
{"learn":[1.202516632],"iteration":90,"passed_time":0.625346918,"remaining_time":0.5497555323},
{"learn":[1.202405149],"iteration":91,"passed_time":0.6317326251,"remaining_time":0.5424660586},
{"learn":[1.202292112],"iteration":92,"passed_time":0.6381829128,"remaining_time":0.5352501849},
{"learn":[1.202163855],"iteration":93,"passed_time":0.6438434971,"remaining_time":0.5274037157},
{"learn":[1.20203129],"iteration":94,"passed_time":0.6497358798,"remaining_time":0.5197887038},
{"learn":[1.201924636],"iteration":95,"passed_time":0.6583289565,"remaining_time":0.5143194972},
{"learn":[1.201835572],"iteration":96,"passed_time":0.6637653208,"remaining_time":0.5063776674},
{"learn":[1.20176382],"iteration":97,"passed_time":0.6687684771,"remaining_time":0.4981642738},
{"learn":[1.201659804],"iteration":98,"passed_time":0.6745399401,"remaining_time":0.4905745019},
{"learn":[1.201553073],"iteration":99,"passed_time":0.680690101,"remaining_time":0.4832899717},
{"learn":[1.201464192],"iteration":100,"passed_time":0.6868355491,"remaining_time":0.476024638},
{"learn":[1.201401651],"iteration":101,"passed_time":0.6921095096,"remaining_time":0.4681917271},
{"learn":[1.20129611],"iteration":102,"passed_time":0.7003217142,"remaining_time":0.4623483162},
{"learn":[1.201233426],"iteration":103,"passed_time":0.7053372172,"remaining_time":0.454399938},
{"learn":[1.201174169],"iteration":104,"passed_time":0.7110491695,"remaining_time":0.4469451923},
{"learn":[1.201032026],"iteration":105,"passed_time":0.7309147433,"remaining_time":0.4482024369},
{"learn":[1.200910967],"iteration":106,"passed_time":0.736670066,"remaining_time":0.4406250862},
{"learn":[1.200817249],"iteration":107,"passed_time":0.7443146472,"remaining_time":0.4341835442},
{"learn":[1.200704232],"iteration":108,"passed_time":0.7498599604,"remaining_time":0.426525849},
{"learn":[1.200621801],"iteration":109,"passed_time":0.7551031416,"remaining_time":0.4187390149},
{"learn":[1.200537844],"iteration":110,"passed_time":0.7606584308,"remaining_time":0.4111667194},
{"learn":[1.200447505],"iteration":111,"passed_time":0.766338112,"remaining_time":0.4036959697},
{"learn":[1.20032417],"iteration":112,"passed_time":0.7718884113,"remaining_time":0.396190512},
{"learn":[1.200308747],"iteration":113,"passed_time":0.776934897,"remaining_time":0.3884674485},
{"learn":[1.200220773],"iteration":114,"passed_time":0.7828005808,"remaining_time":0.3811898481},
{"learn":[1.200059558],"iteration":115,"passed_time":0.7901962332,"remaining_time":0.3746620071},
{"learn":[1.199962202],"iteration":116,"passed_time":0.7957431695,"remaining_time":0.3672660782},
{"learn":[1.199830603],"iteration":117,"passed_time":0.8018336561,"remaining_time":0.3601456252},
{"learn":[1.199723541],"iteration":118,"passed_time":0.8073689321,"remaining_time":0.3527998695},
{"learn":[1.19965165],"iteration":119,"passed_time":0.813154932,"remaining_time":0.3455908461},
{"learn":[1.199569943],"iteration":120,"passed_time":0.8187510164,"remaining_time":0.3383268663},
{"learn":[1.19948939],"iteration":121,"passed_time":0.8241119429,"remaining_time":0.3309957804},
{"learn":[1.199396769],"iteration":122,"passed_time":0.8322308349,"remaining_time":0.3247730088},
{"learn":[1.199272343],"iteration":123,"passed_time":0.8378971035,"remaining_time":0.3175900312},
{"learn":[1.199208133],"iteration":124,"passed_time":0.8435661495,"remaining_time":0.310432343},
{"learn":[1.199109394],"iteration":125,"passed_time":0.8494787184,"remaining_time":0.3033852566},
{"learn":[1.198979611],"iteration":126,"passed_time":0.8557102908,"remaining_time":0.2964665574},
{"learn":[1.198870763],"iteration":127,"passed_time":0.8614940688,"remaining_time":0.2894081637},
{"learn":[1.19877364],"iteration":128,"passed_time":0.8699211013,"remaining_time":0.283230126},
{"learn":[1.198616158],"iteration":129,"passed_time":0.8757045922,"remaining_time":0.276183756},
{"learn":[1.198543054],"iteration":130,"passed_time":0.8816984936,"remaining_time":0.2692209141},
{"learn":[1.198411592],"iteration":131,"passed_time":0.8875981152,"remaining_time":0.2622448977},
{"learn":[1.198312533],"iteration":132,"passed_time":0.8929222894,"remaining_time":0.2551206541},
{"learn":[1.198164042],"iteration":133,"passed_time":0.8985410562,"remaining_time":0.24810462},
{"learn":[1.198029888],"iteration":134,"passed_time":0.9042579388,"remaining_time":0.2411354503},
{"learn":[1.197922774],"iteration":135,"passed_time":0.9100914076,"remaining_time":0.2342147005},
{"learn":[1.197846577],"iteration":136,"passed_time":0.9175926622,"remaining_time":0.2277237264},
{"learn":[1.197756672],"iteration":137,"passed_time":0.9239022616,"remaining_time":0.2209331495},
{"learn":[1.197595058],"iteration":138,"passed_time":0.9301402523,"remaining_time":0.2141330077},
{"learn":[1.197474881],"iteration":139,"passed_time":0.9375141431,"remaining_time":0.2075924174},
{"learn":[1.197360025],"iteration":140,"passed_time":0.9432097989,"remaining_time":0.2006829359},
{"learn":[1.197331013],"iteration":141,"passed_time":0.9480700027,"remaining_time":0.1936199301},
{"learn":[1.197215985],"iteration":142,"passed_time":0.9535707543,"remaining_time":0.1867131547},
{"learn":[1.197116913],"iteration":143,"passed_time":0.9591177689,"remaining_time":0.1798345817},
{"learn":[1.196965489],"iteration":144,"passed_time":0.9648952009,"remaining_time":0.1730156912},
{"learn":[1.196818691],"iteration":145,"passed_time":0.9728776254,"remaining_time":0.1665886345},
{"learn":[1.196661293],"iteration":146,"passed_time":0.9794919759,"remaining_time":0.1599170573},
{"learn":[1.196522136],"iteration":147,"passed_time":0.9858479967,"remaining_time":0.1532061076},
{"learn":[1.196482948],"iteration":148,"passed_time":0.991516531,"remaining_time":0.146398414},
{"learn":[1.196410947],"iteration":149,"passed_time":0.9971815887,"remaining_time":0.1396054224},
{"learn":[1.196282784],"iteration":150,"passed_time":1.002938277,"remaining_time":0.1328395069},
{"learn":[1.19610222],"iteration":151,"passed_time":1.008885819,"remaining_time":0.1261107274},
{"learn":[1.195957634],"iteration":152,"passed_time":1.01487914,"remaining_time":0.1193975458},
{"learn":[1.19582971],"iteration":153,"passed_time":1.033156088,"remaining_time":0.114049698},
{"learn":[1.195811415],"iteration":154,"passed_time":1.040255336,"remaining_time":0.1073811959},
{"learn":[1.195784775],"iteration":155,"passed_time":1.046586696,"remaining_time":0.1006333361},
{"learn":[1.195760347],"iteration":156,"passed_time":1.076742063,"remaining_time":0.09601521585},
{"learn":[1.19562017],"iteration":157,"passed_time":1.0824796,"remaining_time":0.08906477725},
{"learn":[1.195470107],"iteration":158,"passed_time":1.088663502,"remaining_time":0.0821632832},
{"learn":[1.195364735],"iteration":159,"passed_time":1.094531028,"remaining_time":0.07524900821},
{"learn":[1.19523263],"iteration":160,"passed_time":1.114584487,"remaining_time":0.06922885012},
{"learn":[1.195109609],"iteration":161,"passed_time":1.120259724,"remaining_time":0.06223665135},
{"learn":[1.195101164],"iteration":162,"passed_time":1.125626879,"remaining_time":0.05524549099},
{"learn":[1.194971954],"iteration":163,"passed_time":1.132106108,"remaining_time":0.04832160217},
{"learn":[1.194843217],"iteration":164,"passed_time":1.137809769,"remaining_time":0.04137490068},
{"learn":[1.194744788],"iteration":165,"passed_time":1.144199152,"remaining_time":0.03446382987},
{"learn":[1.194719589],"iteration":166,"passed_time":1.15014792,"remaining_time":0.02754845318},
{"learn":[1.194579114],"iteration":167,"passed_time":1.159298412,"remaining_time":0.02070175736},
{"learn":[1.194391627],"iteration":168,"passed_time":1.165398706,"remaining_time":0.01379170067},
{"learn":[1.194236697],"iteration":169,"passed_time":1.171422828,"remaining_time":0.006890722517},
{"learn":[1.194093933],"iteration":170,"passed_time":1.178189314,"remaining_time":0}
]}